[{"accuracy": 0.9983, "Layer1": {"[[0, 1, 2, 3, 4, 5, 6, 7], [8, 9, 10, 11, 12, 13, 14, 15]]": 0.846, "[[0, 1], [2, 3]]": 0.7728, "[[0], [1]]": 0.7612}, "Layer2": {"[[0, 1, 2, 3, 4, 5, 6, 7], [8, 9, 10, 11, 12, 13, 14, 15]]": 0.4784, "[[0, 1], [2, 3]]": 0.5001, "[[0], [1]]": 0.4942}, "Layer3": {"[[0, 1, 2, 3, 4, 5, 6, 7], [8, 9, 10, 11, 12, 13, 14, 15]]": 0.5026, "[[0, 1], [2, 3]]": 0.5033, "[[0], [1]]": 0.4999}}, {"accuracy": 0.9983, "Layer1": {"[[0, 1, 2, 3, 4, 5, 6, 7], [8, 9, 10, 11, 12, 13, 14, 15]]": 0.8571, "[[0, 1], [2, 3]]": 0.8473, "[[0], [1]]": 0.8173}, "Layer2": {"[[0, 1, 2, 3, 4, 5, 6, 7], [8, 9, 10, 11, 12, 13, 14, 15]]": 0.5476, "[[0, 1], [2, 3]]": 0.5127, "[[0], [1]]": 0.5073}, "Layer3": {"[[0, 1, 2, 3, 4, 5, 6, 7], [8, 9, 10, 11, 12, 13, 14, 15]]": 0.4881, "[[0, 1], [2, 3]]": 0.5022, "[[0], [1]]": 0.4983}}, {"accuracy": 0.9906, "Layer1": {"[[0, 1, 2, 3, 4, 5, 6, 7], [8, 9, 10, 11, 12, 13, 14, 15]]": 0.6798, "[[0, 1], [2, 3]]": 0.6313, "[[0], [1]]": 0.5542}, "Layer2": {"[[0, 1, 2, 3, 4, 5, 6, 7], [8, 9, 10, 11, 12, 13, 14, 15]]": 0.6326, "[[0, 1], [2, 3]]": 0.6101, "[[0], [1]]": 0.6353}, "Layer3": {"[[0, 1, 2, 3, 4, 5, 6, 7], [8, 9, 10, 11, 12, 13, 14, 15]]": 0.4996, "[[0, 1], [2, 3]]": 0.4999, "[[0], [1]]": 0.5055}}, {"accuracy": 0.9955, "Layer1": {"[[0, 1, 2, 3, 4, 5, 6, 7], [8, 9, 10, 11, 12, 13, 14, 15]]": 0.7872, "[[0, 1], [2, 3]]": 0.7348, "[[0], [1]]": 0.7295}, "Layer2": {"[[0, 1, 2, 3, 4, 5, 6, 7], [8, 9, 10, 11, 12, 13, 14, 15]]": 0.5403, "[[0, 1], [2, 3]]": 0.5441, "[[0], [1]]": 0.5191}, "Layer3": {"[[0, 1, 2, 3, 4, 5, 6, 7], [8, 9, 10, 11, 12, 13, 14, 15]]": 0.4838, "[[0, 1], [2, 3]]": 0.5003, "[[0], [1]]": 0.4945}}, {"accuracy": 0.9864, "Layer1": {"[[0, 1, 2, 3, 4, 5, 6, 7], [8, 9, 10, 11, 12, 13, 14, 15]]": 0.6973, "[[0, 1], [2, 3]]": 0.6639, "[[0], [1]]": 0.641}, "Layer2": {"[[0, 1, 2, 3, 4, 5, 6, 7], [8, 9, 10, 11, 12, 13, 14, 15]]": 0.6411, "[[0, 1], [2, 3]]": 0.644, "[[0], [1]]": 0.6295}, "Layer3": {"[[0, 1, 2, 3, 4, 5, 6, 7], [8, 9, 10, 11, 12, 13, 14, 15]]": 0.5056, "[[0, 1], [2, 3]]": 0.4936, "[[0], [1]]": 0.5117}}, {"accuracy": 0.9995, "Layer1": {"[[0, 1, 2, 3, 4, 5, 6, 7], [8, 9, 10, 11, 12, 13, 14, 15]]": 0.975, "[[0, 1], [2, 3]]": 0.9533, "[[0], [1]]": 0.9303}, "Layer2": {"[[0, 1, 2, 3, 4, 5, 6, 7], [8, 9, 10, 11, 12, 13, 14, 15]]": 0.732, "[[0, 1], [2, 3]]": 0.6909, "[[0], [1]]": 0.5119}, "Layer3": {"[[0, 1, 2, 3, 4, 5, 6, 7], [8, 9, 10, 11, 12, 13, 14, 15]]": 0.4746, "[[0, 1], [2, 3]]": 0.4954, "[[0], [1]]": 0.4943}}, {"accuracy": 0.9979, "Layer1": {"[[0, 1, 2, 3, 4, 5, 6, 7], [8, 9, 10, 11, 12, 13, 14, 15]]": 0.9398, "[[0, 1], [2, 3]]": 0.821, "[[0], [1]]": 0.7909}, "Layer2": {"[[0, 1, 2, 3, 4, 5, 6, 7], [8, 9, 10, 11, 12, 13, 14, 15]]": 0.5514, "[[0, 1], [2, 3]]": 0.5192, "[[0], [1]]": 0.5105}, "Layer3": {"[[0, 1, 2, 3, 4, 5, 6, 7], [8, 9, 10, 11, 12, 13, 14, 15]]": 0.5058, "[[0, 1], [2, 3]]": 0.4982, "[[0], [1]]": 0.4975}}, {"accuracy": 0.996, "Layer1": {"[[0, 1, 2, 3, 4, 5, 6, 7], [8, 9, 10, 11, 12, 13, 14, 15]]": 0.8371, "[[0, 1], [2, 3]]": 0.7824, "[[0], [1]]": 0.679}, "Layer2": {"[[0, 1, 2, 3, 4, 5, 6, 7], [8, 9, 10, 11, 12, 13, 14, 15]]": 0.626, "[[0, 1], [2, 3]]": 0.6357, "[[0], [1]]": 0.5846}, "Layer3": {"[[0, 1, 2, 3, 4, 5, 6, 7], [8, 9, 10, 11, 12, 13, 14, 15]]": 0.4925, "[[0, 1], [2, 3]]": 0.4879, "[[0], [1]]": 0.506}}, {"accuracy": 0.9975, "Layer1": {"[[0, 1, 2, 3, 4, 5, 6, 7], [8, 9, 10, 11, 12, 13, 14, 15]]": 0.7897, "[[0, 1], [2, 3]]": 0.7651, "[[0], [1]]": 0.7636}, "Layer2": {"[[0, 1, 2, 3, 4, 5, 6, 7], [8, 9, 10, 11, 12, 13, 14, 15]]": 0.6661, "[[0, 1], [2, 3]]": 0.6473, "[[0], [1]]": 0.5454}, "Layer3": {"[[0, 1, 2, 3, 4, 5, 6, 7], [8, 9, 10, 11, 12, 13, 14, 15]]": 0.5024, "[[0, 1], [2, 3]]": 0.4988, "[[0], [1]]": 0.4897}}, {"accuracy": 0.9965, "Layer1": {"[[0, 1, 2, 3, 4, 5, 6, 7], [8, 9, 10, 11, 12, 13, 14, 15]]": 0.6748, "[[0, 1], [2, 3]]": 0.7359, "[[0], [1]]": 0.721}, "Layer2": {"[[0, 1, 2, 3, 4, 5, 6, 7], [8, 9, 10, 11, 12, 13, 14, 15]]": 0.5209, "[[0, 1], [2, 3]]": 0.5037, "[[0], [1]]": 0.5037}, "Layer3": {"[[0, 1, 2, 3, 4, 5, 6, 7], [8, 9, 10, 11, 12, 13, 14, 15]]": 0.4987, "[[0, 1], [2, 3]]": 0.5165, "[[0], [1]]": 0.4975}}]